{
    "Ar40AX": {
        "error": 0.006484103200428949, 
        "fit": "previous", 
        "references": [
            {
                "exclude": false, 
                "record_id": "bu-FC-J-7502"
            }
        ], 
        "value": 0.7462436141138059
    }, 
    "Ar40H1": {
        "error": 0.006484103200428949, 
        "fit": "previous", 
        "references": [
            {
                "exclude": false, 
                "record_id": "bu-FC-J-7502"
            }
        ], 
        "value": 0.7462436141138059
    }, 
    "Ar40L2": {
        "error": 0.006484103200428949, 
        "fit": "previous", 
        "references": [
            {
                "exclude": false, 
                "record_id": "bu-FC-J-7502"
            }
        ], 
        "value": 0.7462436141138059
    }
}