{
    "Ar36": {
        "error": 0.0005378762310528391, 
        "filter_outliers_dict": {
            "filter_outliers": true, 
            "iterations": 1, 
            "std_devs": 2
        }, 
        "fit": "Linear", 
        "value": 0.03793662812789719
    }, 
    "Ar37": {
        "error": 0.009934950785535182, 
        "filter_outliers_dict": {
            "filter_outliers": true, 
            "iterations": 1, 
            "std_devs": 2
        }, 
        "fit": "linear", 
        "value": 1.1662922827692834
    }, 
    "Ar38": {
        "error": 0.0043260917134822835, 
        "filter_outliers_dict": {
            "filter_outliers": true, 
            "iterations": 1, 
            "std_devs": 2
        }, 
        "fit": "linear", 
        "value": 1.094732092537205
    }, 
    "Ar39": {
        "error": 0.016316328259311615, 
        "filter_outliers_dict": {
            "filter_outliers": true, 
            "iterations": 1, 
            "std_devs": 2
        }, 
        "fit": "Linear", 
        "value": 86.51808375436606
    }, 
    "Ar40": {
        "error": 0.03140687878720522, 
        "filter_outliers_dict": {
            "filter_outliers": true, 
            "iterations": 1, 
            "std_devs": 2
        }, 
        "fit": "Linear", 
        "value": 375.95567887010355
    }, 
    "PM41": {
        "error": 0.06798872581663795, 
        "filter_outliers_dict": {
            "filter_outliers": false, 
            "iterations": 1, 
            "std_devs": 2
        }, 
        "fit": "linear", 
        "value": -0.1743849346782295
    }
}