{
    "Ar36": {
        "error": 0.0005386996849881204, 
        "filter_outliers_dict": {
            "filter_outliers": true, 
            "iterations": 1, 
            "std_devs": 2
        }, 
        "fit": "Linear", 
        "value": 0.04664343537103704
    }, 
    "Ar37": {
        "error": 0.01076601536462226, 
        "filter_outliers_dict": {
            "filter_outliers": true, 
            "iterations": 1, 
            "std_devs": 2
        }, 
        "fit": "linear", 
        "value": 1.305004887402484
    }, 
    "Ar38": {
        "error": 0.0053057499180925475, 
        "filter_outliers_dict": {
            "filter_outliers": true, 
            "iterations": 1, 
            "std_devs": 2
        }, 
        "fit": "linear", 
        "value": 2.7695727300158466
    }, 
    "Ar39": {
        "error": 0.027477517150514868, 
        "filter_outliers_dict": {
            "filter_outliers": true, 
            "iterations": 1, 
            "std_devs": 2
        }, 
        "fit": "Linear", 
        "value": 214.09019672215217
    }, 
    "Ar40": {
        "error": 0.05967001739478058, 
        "filter_outliers_dict": {
            "filter_outliers": true, 
            "iterations": 1, 
            "std_devs": 2
        }, 
        "fit": "Linear", 
        "value": 875.650179175353
    }, 
    "PM41": {
        "error": 0.06679011617378308, 
        "filter_outliers_dict": {
            "filter_outliers": false, 
            "iterations": 1, 
            "std_devs": 2
        }, 
        "fit": "linear", 
        "value": -0.11840769827706908
    }
}