{
    "Ar36": {
        "error": 0.0004540586939744537, 
        "filter_outliers_dict": {
            "filter_outliers": true, 
            "iterations": 1, 
            "std_devs": 2
        }, 
        "fit": "Linear", 
        "value": 0.032325097885395455
    }, 
    "Ar37": {
        "error": 0.008745783529186148, 
        "filter_outliers_dict": {
            "filter_outliers": true, 
            "iterations": 1, 
            "std_devs": 2
        }, 
        "fit": "linear", 
        "value": 1.7481387132761967
    }, 
    "Ar38": {
        "error": 0.006032323770303438, 
        "filter_outliers_dict": {
            "filter_outliers": true, 
            "iterations": 1, 
            "std_devs": 2
        }, 
        "fit": "linear", 
        "value": 3.786687788927202
    }, 
    "Ar39": {
        "error": 0.03245002473138526, 
        "filter_outliers_dict": {
            "filter_outliers": true, 
            "iterations": 1, 
            "std_devs": 2
        }, 
        "fit": "Linear", 
        "value": 296.69190941558907
    }, 
    "Ar40": {
        "error": 0.06766070986885601, 
        "filter_outliers_dict": {
            "filter_outliers": true, 
            "iterations": 1, 
            "std_devs": 2
        }, 
        "fit": "Linear", 
        "value": 1206.1002747654045
    }, 
    "PM41": {
        "error": 0.07118029461299008, 
        "filter_outliers_dict": {
            "filter_outliers": false, 
            "iterations": 1, 
            "std_devs": 2
        }, 
        "fit": "linear", 
        "value": -0.1099306725707225
    }
}