{
    "Ar36": {
        "error": 0.00044200105809525216, 
        "filter_outliers_dict": {
            "filter_outliers": true, 
            "iterations": 1, 
            "std_devs": 2
        }, 
        "fit": "Linear", 
        "value": 0.031494675343534326
    }, 
    "Ar37": {
        "error": 0.010567594855169624, 
        "filter_outliers_dict": {
            "filter_outliers": true, 
            "iterations": 1, 
            "std_devs": 2
        }, 
        "fit": "linear", 
        "value": 0.8710939565914799
    }, 
    "Ar38": {
        "error": 0.004589198839004486, 
        "filter_outliers_dict": {
            "filter_outliers": true, 
            "iterations": 1, 
            "std_devs": 2
        }, 
        "fit": "linear", 
        "value": 1.297921862382843
    }, 
    "Ar39": {
        "error": 0.022917168774954977, 
        "filter_outliers_dict": {
            "filter_outliers": true, 
            "iterations": 1, 
            "std_devs": 2
        }, 
        "fit": "Linear", 
        "value": 101.27919264038263
    }, 
    "Ar40": {
        "error": 0.03856610241384736, 
        "filter_outliers_dict": {
            "filter_outliers": true, 
            "iterations": 1, 
            "std_devs": 2
        }, 
        "fit": "Linear", 
        "value": 424.8979238368679
    }, 
    "PM41": {
        "error": 0.06822588421028727, 
        "filter_outliers_dict": {
            "filter_outliers": false, 
            "iterations": 1, 
            "std_devs": 2
        }, 
        "fit": "linear", 
        "value": -0.13025332664725178
    }
}