{
    "AX": {
        "error": 0.006626554366662053, 
        "filter_outliers_dict": {
            "filter_outliers": true, 
            "iterations": 1, 
            "std_devs": 2
        }, 
        "fit": "average", 
        "value": -0.06992816883093075
    }, 
    "CDD": {
        "error": 7.157433030002413e-06, 
        "filter_outliers_dict": {
            "filter_outliers": true, 
            "iterations": 1, 
            "std_devs": 10
        }, 
        "fit": "average", 
        "value": 1.7367631354180682e-05
    }, 
    "H1": {
        "error": 0.005734208064680748, 
        "filter_outliers_dict": {
            "filter_outliers": true, 
            "iterations": 1, 
            "std_devs": 2
        }, 
        "fit": "average", 
        "value": -0.04455249062692417
    }, 
    "H2": {
        "error": 0.007690623452664768, 
        "filter_outliers_dict": {
            "filter_outliers": true, 
            "iterations": 1, 
            "std_devs": 2
        }, 
        "fit": "average", 
        "value": -0.1913897410351838
    }, 
    "L1": {
        "error": 0.002656820204074216, 
        "filter_outliers_dict": {
            "filter_outliers": true, 
            "iterations": 1, 
            "std_devs": 2
        }, 
        "fit": "average", 
        "value": -0.015226543748113417
    }, 
    "L2": {
        "error": 0.005193535817025172, 
        "filter_outliers_dict": {
            "filter_outliers": true, 
            "iterations": 1, 
            "std_devs": 2
        }, 
        "fit": "average", 
        "value": -0.030530194758808325
    }
}