{
    "AX": {
        "error": 0.006834732476099345, 
        "filter_outliers_dict": {
            "filter_outliers": true, 
            "iterations": 1, 
            "std_devs": 2
        }, 
        "fit": "average", 
        "value": -0.07516099430579003
    }, 
    "CDD": {
        "error": 3.0369853361416206e-05, 
        "filter_outliers_dict": {
            "filter_outliers": true, 
            "iterations": 1, 
            "std_devs": 10
        }, 
        "fit": "average", 
        "value": 0.00034735263404010074
    }, 
    "H1": {
        "error": 0.005233766903508558, 
        "filter_outliers_dict": {
            "filter_outliers": true, 
            "iterations": 1, 
            "std_devs": 2
        }, 
        "fit": "average", 
        "value": 0.0034688549830529784
    }, 
    "H2": {
        "error": 0.009205198479914202, 
        "filter_outliers_dict": {
            "filter_outliers": true, 
            "iterations": 1, 
            "std_devs": 2
        }, 
        "fit": "average", 
        "value": -0.19371559328848775
    }, 
    "L1": {
        "error": 0.0028576379487795073, 
        "filter_outliers_dict": {
            "filter_outliers": true, 
            "iterations": 1, 
            "std_devs": 2
        }, 
        "fit": "average", 
        "value": -0.022696526079692327
    }, 
    "L2": {
        "error": 0.005775620829004587, 
        "filter_outliers_dict": {
            "filter_outliers": true, 
            "iterations": 1, 
            "std_devs": 2
        }, 
        "fit": "average", 
        "value": -0.027454596139052847
    }
}